{
  "project_info": {
    "project_number": "171207399152",
    "firebase_url": "https://perfect-1morecode.firebaseio.com",
    "project_id": "perfect-1morecode",
    "storage_bucket": "perfect-1morecode.appspot.com"
  },
  "client": [
    {
      "client_info": {
        "mobilesdk_app_id": "1:171207399152:android:965ae8a0d72b375144d435",
        "android_client_info": {
          "package_name": "com.onemorecode.message_app"
        }
      },
      "oauth_client": [
        {
          "client_id": "171207399152-v2ug9dhi4bv1ja5tbum8s867vbquabth.apps.googleusercontent.com",
          "client_type": 1,
          "android_info": {
            "package_name": "com.onemorecode.message_app",
            "certificate_hash": "13556e86d852fa5f87846bbbb6236533543aba11"
          }
        },
        {
          "client_id": "171207399152-i0nsgc78slbe40bnleqa1g3gojg6d0bv.apps.googleusercontent.com",
          "client_type": 3
        }
      ],
      "api_key": [
        {
          "current_key": "AIzaSyDRt2FgBdgXJQW_JW8eilRiUnbawmoIWT4"
        }
      ],
      "services": {
        "appinvite_service": {
          "other_platform_oauth_client": [
            {
              "client_id": "171207399152-i0nsgc78slbe40bnleqa1g3gojg6d0bv.apps.googleusercontent.com",
              "client_type": 3
            },
            {
              "client_id": "171207399152-92l8lpl5jcmkh6e2qqmlqnd39t7ckq2i.apps.googleusercontent.com",
              "client_type": 2,
              "ios_info": {
                "bundle_id": "com.onemorecode.messageApp"
              }
            }
          ]
        }
      }
    },
    {
      "client_info": {
        "mobilesdk_app_id": "1:171207399152:android:ddacd0f76189fbf944d435",
        "android_client_info": {
          "package_name": "hollywood.app.za.spors.be"
        }
      },
      "oauth_client": [
        {
          "client_id": "171207399152-b9050cm7bm0skj1sjslj2br5erf2a141.apps.googleusercontent.com",
          "client_type": 1,
          "android_info": {
            "package_name": "hollywood.app.za.spors.be",
            "certificate_hash": "83ae90500d76c1a12974926f14c52736471cfa0c"
          }
        },
        {
          "client_id": "171207399152-i0nsgc78slbe40bnleqa1g3gojg6d0bv.apps.googleusercontent.com",
          "client_type": 3
        }
      ],
      "api_key": [
        {
          "current_key": "AIzaSyDRt2FgBdgXJQW_JW8eilRiUnbawmoIWT4"
        }
      ],
      "services": {
        "appinvite_service": {
          "other_platform_oauth_client": [
            {
              "client_id": "171207399152-i0nsgc78slbe40bnleqa1g3gojg6d0bv.apps.googleusercontent.com",
              "client_type": 3
            },
            {
              "client_id": "171207399152-92l8lpl5jcmkh6e2qqmlqnd39t7ckq2i.apps.googleusercontent.com",
              "client_type": 2,
              "ios_info": {
                "bundle_id": "com.onemorecode.messageApp"
              }
            }
          ]
        }
      }
    }
  ],
  "configuration_version": "1"
}